[
    {
        "key": "group_65cdd19d4d554",
        "title": "Information Slider",
        "fields": [
            {
                "key": "field_65cf2d1749497",
                "label": "Information slider structure",
                "name": "information_slider_structure",
                "aria-label": "",
                "type": "group",
                "instructions": "",
                "required": 0,
                "conditional_logic": 0,
                "wrapper": {
                    "width": "",
                    "class": "",
                    "id": ""
                },
                "layout": "block",
                "sub_fields": [
                    {
                        "key": "field_65cf2d4b49498",
                        "label": "Slides",
                        "name": "slides",
                        "aria-label": "",
                        "type": "repeater",
                        "instructions": "",
                        "required": 0,
                        "conditional_logic": 0,
                        "wrapper": {
                            "width": "",
                            "class": "",
                            "id": ""
                        },
                        "layout": "block",
                        "pagination": 0,
                        "min": 0,
                        "max": 0,
                        "collapsed": "",
                        "button_label": "Add slide",
                        "rows_per_page": 20,
                        "sub_fields": [
                            {
                                "key": "field_65cf2d8049499",
                                "label": "Slide case",
                                "name": "slide_case",
                                "aria-label": "",
                                "type": "text",
                                "instructions": "",
                                "required": 0,
                                "conditional_logic": 0,
                                "wrapper": {
                                    "width": "",
                                    "class": "",
                                    "id": ""
                                },
                                "default_value": "",
                                "maxlength": "",
                                "placeholder": "",
                                "prepend": "",
                                "append": "",
                                "parent_repeater": "field_65cf2d4b49498"
                            },
                            {
                                "key": "field_65cf2dbe4949a",
                                "label": "Slide title",
                                "name": "slide_title",
                                "aria-label": "",
                                "type": "text",
                                "instructions": "",
                                "required": 0,
                                "conditional_logic": 0,
                                "wrapper": {
                                    "width": "",
                                    "class": "",
                                    "id": ""
                                },
                                "default_value": "",
                                "maxlength": "",
                                "placeholder": "",
                                "prepend": "",
                                "append": "",
                                "parent_repeater": "field_65cf2d4b49498"
                            },
                            {
                                "key": "field_65cf2dcb4949b",
                                "label": "Slide text",
                                "name": "slide_text",
                                "aria-label": "",
                                "type": "text",
                                "instructions": "",
                                "required": 0,
                                "conditional_logic": 0,
                                "wrapper": {
                                    "width": "",
                                    "class": "",
                                    "id": ""
                                },
                                "default_value": "",
                                "maxlength": "",
                                "placeholder": "",
                                "prepend": "",
                                "append": "",
                                "parent_repeater": "field_65cf2d4b49498"
                            },
                            {
                                "key": "field_65cf2dd44949c",
                                "label": "Slide image",
                                "name": "slide_image",
                                "aria-label": "",
                                "type": "image",
                                "instructions": "",
                                "required": 0,
                                "conditional_logic": 0,
                                "wrapper": {
                                    "width": "",
                                    "class": "",
                                    "id": ""
                                },
                                "return_format": "id",
                                "library": "all",
                                "min_width": "",
                                "min_height": "",
                                "min_size": "",
                                "max_width": "",
                                "max_height": "",
                                "max_size": "",
                                "mime_types": "",
                                "preview_size": "medium",
                                "parent_repeater": "field_65cf2d4b49498"
                            }
                        ]
                    },
                    {
                        "key": "field_65cf2dfc4949d",
                        "label": "Slide links",
                        "name": "slide_links",
                        "aria-label": "",
                        "type": "group",
                        "instructions": "",
                        "required": 0,
                        "conditional_logic": 0,
                        "wrapper": {
                            "width": "",
                            "class": "",
                            "id": ""
                        },
                        "layout": "block",
                        "sub_fields": [
                            {
                                "key": "field_65cf2e154949e",
                                "label": "Contact link",
                                "name": "contact_link",
                                "aria-label": "",
                                "type": "link",
                                "instructions": "",
                                "required": 0,
                                "conditional_logic": 0,
                                "wrapper": {
                                    "width": "",
                                    "class": "",
                                    "id": ""
                                },
                                "return_format": "array"
                            },
                            {
                                "key": "field_65cf2e444949f",
                                "label": "Cases link",
                                "name": "cases_link",
                                "aria-label": "",
                                "type": "link",
                                "instructions": "",
                                "required": 0,
                                "conditional_logic": 0,
                                "wrapper": {
                                    "width": "",
                                    "class": "",
                                    "id": ""
                                },
                                "return_format": "array"
                            }
                        ]
                    }
                ]
            }
        ],
        "location": [
            [
                {
                    "param": "block",
                    "operator": "==",
                    "value": "acf\/information-slider-structure"
                }
            ]
        ],
        "menu_order": 0,
        "position": "normal",
        "style": "default",
        "label_placement": "top",
        "instruction_placement": "label",
        "hide_on_screen": "",
        "active": true,
        "description": "",
        "show_in_rest": 0
    }
]
